{
  "export_time": "2025-12-09T17:42:26.820228",
  "session_summary": {
    "session_start": "2025-12-09T17:40:49.981489",
    "total_trades": 2,
    "wins": 1,
    "losses": 1,
    "win_rate": 50.0,
    "rolling_win_rate": 50.0,
    "total_profit": -0.58,
    "profit_factor": 0.5166666666666667,
    "max_drawdown": 0.012395951482253415,
    "best_hours": [],
    "martingale_success_rate": 0.0,
    "hourly_profits": {
      "0": 0.0,
      "1": 0.0,
      "2": 0.0,
      "3": 0.0,
      "4": 0.0,
      "5": 0.0,
      "6": 0.0,
      "7": 0.0,
      "8": 0.0,
      "9": 0.0,
      "10": 0.0,
      "11": 0.0,
      "12": 0.0,
      "13": 0.0,
      "14": 0.0,
      "15": 0.0,
      "16": 0.0,
      "17": -0.58,
      "18": 0.0,
      "19": 0.0,
      "20": 0.0,
      "21": 0.0,
      "22": 0.0,
      "23": 0.0
    }
  },
  "martingale_stats": {
    "recovery_attempts": 0,
    "recovery_success": 0,
    "max_level_reached": 0
  },
  "trades": [
    {
      "date": "2025-12-09",
      "time": "17:41:48",
      "symbol": "R_100",
      "direction": "SELL",
      "entry_price": 0.0,
      "exit_price": 608.7,
      "stake": 1.2,
      "payout": 1.8199999999999998,
      "profit": 0.62,
      "result": "WIN",
      "martingale_level": 0,
      "balance_before": 9680.58,
      "balance_after": 9680.58,
      "win_rate": 100.0,
      "strategy": "AMT",
      "confidence": 0.7,
      "confluence": 50.0
    },
    {
      "date": "2025-12-09",
      "time": "17:42:26",
      "symbol": "R_100",
      "direction": "SELL",
      "entry_price": 0.0,
      "exit_price": 608.71,
      "stake": 1.2,
      "payout": 0,
      "profit": -1.2,
      "result": "LOSS",
      "martingale_level": 1,
      "balance_before": 9679.38,
      "balance_after": 9679.38,
      "win_rate": 50.0,
      "strategy": "AMT",
      "confidence": 0.7,
      "confluence": 50.0
    }
  ]
}